{
  "name": "AdminProfil",
  "fields": [
    {
      "fieldName": "code",
      "fieldType": "String",
      "fieldValidateRules": [
        "required"
      ]
    },
    {
      "fieldName": "libelle",
      "fieldType": "String",
      "fieldValidateRules": [
        "required"
      ]
    },
    {
      "fieldName": "description",
      "fieldType": "String"
    }
  ],
  "relationships": [],
  "changelogDate": "20210301081031",
  "entityTableName": "admin_profil",
  "dto": "no",
  "pagination": "no",
  "service": "no",
  "jpaMetamodelFiltering": false,
  "fluentMethods": true,
  "readOnly": false,
  "embedded": false,
  "clientRootFolder": "",
  "applications": "*"
}
